d2r_image/__init__.py
d2r_image/d2data_data.py
d2r_image/d2data_lookup.py
d2r_image/d2data_ref_lookup.py
d2r_image/data_models.py
d2r_image/demo.py
d2r_image/nip_data.py
d2r_image/nip_helpers.py
d2r_image/nip_lookup.py
d2r_image/ocr.py
d2r_image/ocr_data.py
d2r_image/processing.py
d2r_image/processing_data.py
d2r_image/processing_helpers.py
d2r_image/screen_object_helpers.py
d2r_image/screen_objects.py
d2r_image/resources/__init__.py
d2r_image/resources/demo_images/__init__.py
d2r_image/resources/demo_images/get_health/25.82_79.08.png
d2r_image/resources/demo_images/get_health/46.69_65.png
d2r_image/resources/demo_images/get_health/67.59_0.65.png
d2r_image/resources/demo_images/get_health/80_32.66.png
d2r_image/resources/demo_images/get_health/__init__.py
d2r_image/resources/demo_images/ground/__init__.py
d2r_image/resources/demo_images/ground/ground1.png
d2r_image/resources/demo_images/ground/ground10.png
d2r_image/resources/demo_images/ground/ground11.png
d2r_image/resources/demo_images/ground/ground12.png
d2r_image/resources/demo_images/ground/ground13.png
d2r_image/resources/demo_images/ground/ground2.png
d2r_image/resources/demo_images/ground/ground3.png
d2r_image/resources/demo_images/ground/ground4.png
d2r_image/resources/demo_images/ground/ground5.png
d2r_image/resources/demo_images/ground/ground6.png
d2r_image/resources/demo_images/ground/ground7.png
d2r_image/resources/demo_images/ground/ground8.png
d2r_image/resources/demo_images/ground/ground9.png
d2r_image/resources/demo_images/hover_left/__init__.py
d2r_image/resources/demo_images/hover_left/hover2.png
d2r_image/resources/demo_images/hover_left/hover3.png
d2r_image/resources/demo_images/hover_left/hover6.png
d2r_image/resources/demo_images/hover_right/__init__.py
d2r_image/resources/demo_images/hover_right/hover1.png
d2r_image/resources/demo_images/hover_right/hover10.png
d2r_image/resources/demo_images/hover_right/hover11.png
d2r_image/resources/demo_images/hover_right/hover12.png
d2r_image-0.2.6.dist-info/LICENSE
d2r_image-0.2.6.dist-info/METADATA
d2r_image-0.2.6.dist-info/WHEEL
d2r_image-0.2.6.dist-info/dependency_links.txt
d2r_image-0.2.6.dist-info/top_level.txt
d2r_image-0.2.6.dist-info/RECORD
