Metadata-Version: 2.1
Name: d2r-image
Version: 0.2.6
Summary: D2R Image is a package aimed to help in providing an API for answering common questions when looking at a Diablo II: Resurrected image
Home-page: https://github.com/Ezro/d2r_image
License: UNKNOWN
Platform: UNKNOWN
Classifier: Programming Language :: Python :: 3
Classifier: License :: OSI Approved :: MIT License
Classifier: Operating System :: Microsoft :: Windows :: Windows 10
License-File: LICENSE
Requires-Dist: opencv-python
Requires-Dist: keyboard
Requires-Dist: pyparsing
Requires-Dist: psutil
Requires-Dist: mss
Requires-Dist: tesserocr
Requires-Dist: dataclasses-json
Requires-Dist: parse
Requires-Dist: rapidfuzz
